langgraph/checkpoint/oracle/__init__.py
langgraph/checkpoint/oracle/_ainternal.py
langgraph/checkpoint/oracle/_internal.py
langgraph/checkpoint/oracle/aio.py
langgraph/checkpoint/oracle/base.py
langgraph/checkpoint/oracle/py.typed
langgraph/checkpoint/oracle/utils.py
langgraph_checkpoint_oracle-2.0.0rc7.dist-info/METADATA
langgraph_checkpoint_oracle-2.0.0rc7.dist-info/WHEEL
langgraph_checkpoint_oracle-2.0.0rc7.dist-info/RECORD
