Metadata-Version: 2.1
Name: langgraph-checkpoint-oracle
Version: 2.0.0rc7
Summary: Library with an Oracle Database implementation of LangGraph checkpoint saver.
Home-page: https://github.com/yoshidan/langgraph-checkpoint
License: MIT
Author: yoshidan
Author-email: naohiro.y@gmail.com
Requires-Python: >=3.9.0,<4.0.0
Classifier: License :: OSI Approved :: MIT License
Classifier: Programming Language :: Python :: 3
Classifier: Programming Language :: Python :: 3.9
Classifier: Programming Language :: Python :: 3.10
Classifier: Programming Language :: Python :: 3.11
Classifier: Programming Language :: Python :: 3.12
Requires-Dist: langgraph-checkpoint (>=2.0.21,<3.0.0)
Requires-Dist: oracledb (>=2.0.0,<3.0.0)
Requires-Dist: orjson (>=3.10.1)
Project-URL: Repository, https://github.com/yoshidan/langgraph-checkpoint
